webdown/__init__.py
webdown/cli.py
webdown/config.py
webdown/converter.py
webdown/error_utils.py
webdown/html_parser.py
webdown/markdown_converter.py
webdown/tests/__init__.py
webdown/tests/conftest.py
webdown/tests/test_claude_xml.py
webdown/tests/test_cli.py
webdown/tests/test_config.py
webdown/tests/test_config_combinations.py
webdown/tests/test_converter.py
webdown/tests/test_error_utils.py
webdown/tests/test_errors.py
webdown/tests/test_html_parser.py
webdown/tests/test_integration.py
webdown/tests/test_markdown_converter_extended.py
webdown/tests/test_streaming.py
webdown/tests/test_validation.py
webdown/tests/test_xml_converter.py
webdown/tests/test_xml_converter_extended.py
webdown/validation.py
webdown/xml_converter.py
webdown-0.7.0.dist-info/LICENSE
webdown-0.7.0.dist-info/METADATA
webdown-0.7.0.dist-info/WHEEL
webdown-0.7.0.dist-info/entry_points.txt
webdown-0.7.0.dist-info/RECORD
