Metadata-Version: 2.3
Name: webdown
Version: 0.7.0
Summary: Convert web pages and HTML files to markdown and Claude XML formats
License: MIT
Keywords: web,markdown,html,converter,html-to-markdown,claude-xml,web-scraping,content-extraction,anthropic
Author: Travis Cole
Author-email: kelp@plek.org
Requires-Python: >=3.10,<4.0
Classifier: Development Status :: 4 - Beta
Classifier: Intended Audience :: Developers
Classifier: License :: OSI Approved :: MIT License
Classifier: Operating System :: OS Independent
Classifier: Programming Language :: Python :: 3
Classifier: Programming Language :: Python :: 3.10
Classifier: Programming Language :: Python :: 3.11
Classifier: Programming Language :: Python :: 3.12
Classifier: Programming Language :: Python :: 3.13
Classifier: Topic :: Internet :: WWW/HTTP
Classifier: Topic :: Software Development :: Libraries :: Python Modules
Classifier: Topic :: Text Processing :: Markup :: HTML
Requires-Dist: beautifulsoup4 (>=4.13.3,<5.0.0)
Requires-Dist: html2text (>=2024.2.26,<2025.0.0)
Requires-Dist: requests (>=2.32.3,<3.0.0)
Requires-Dist: tqdm (>=4.67.1,<5.0.0)
Project-URL: Bug Tracker, https://github.com/kelp/webdown/issues
Project-URL: Changelog, https://github.com/kelp/webdown/blob/main/CHANGELOG.md
Project-URL: Documentation, https://tcole.net/webdown/
Project-URL: Homepage, https://tcole.net/webdown
Project-URL: Repository, https://github.com/kelp/webdown
Project-URL: Source Code, https://github.com/kelp/webdown
